MANIFEST.in
README.rst
setup.py
chrw/__init__.py
chrw/exceptions.py
chrw/v1.py
chrw/version.py
chrw.egg-info/PKG-INFO
chrw.egg-info/SOURCES.txt
chrw.egg-info/dependency_links.txt
chrw.egg-info/not-zip-safe
chrw.egg-info/requires.txt
chrw.egg-info/top_level.txt