Metadata-Version: 1.1
Name: chrw
Version: 1.0.1
Summary: Python wrapper for the chr url shortener API
Home-page: https://github.com/plausibility/chrw
Author: plausibility
Author-email: chris@gibsonsec.org
License: MIT
Keywords: chr url wrapper shorten
Platform: UNKNOWN
Classifier: Development Status :: 5 - Production/Stable
Classifier: Intended Audience :: Developers
Classifier: License :: OSI Approved :: MIT License
Classifier: Operating System :: OS Independent
Classifier: Programming Language :: Python :: 2
